README.md
setup.py
pypig/__init__.py
pypig/pypig.py
pypig.egg-info/PKG-INFO
pypig.egg-info/SOURCES.txt
pypig.egg-info/dependency_links.txt
pypig.egg-info/entry_points.txt
pypig.egg-info/not-zip-safe
pypig.egg-info/requires.txt
pypig.egg-info/top_level.txt