Metadata-Version: 2.1
Name: pypig
Version: 1.0.1
Summary: Command line tool for managing private pypiserver
Home-page: https://github.com/CQCL/pypig
Author: Seyon Sivarajah
Author-email: seyon.sivarajah@cambridgequantum.com
License: GPL
Platform: UNKNOWN
Classifier: Programming Language :: Python :: 3
Classifier: License :: OSI Approved :: GNU General Public License (GPL)
Classifier: Operating System :: OS Independent
